[
   
    {
        "id": 1,
        "name": "Dubai (UAE)",
        "flag": "https://upload.wikimedia.org/wikipedia/commons/thumb/c/cb/Flag_of_the_United_Arab_Emirates.svg/1200px-Flag_of_the_United_Arab_Emirates.svg.png",
        "url": "RadioallDubai.json"
    },
    {
        "id": 11,
        "name": "Ghana",
        "flag": "https://c4.wallpaperflare.com/wallpaper/711/208/1002/flag-of-ghana-wallpaper-preview.jpg",
        "url": "ghana_RadioList.json"
    },
    {
        "id": 1,
        "name": "United States of America",
        "flag": "https://encrypted-tbn0.gstatic.com/images?q=tbn:ANd9GcTkOFeS88SuTVfZl3UFMKMApgAnEv_Rv72CS5uSDDJ5Q4IETeBi513nK3d_W5h2M3Icgjw&usqp=CAU",
        "url": "unitedStateRadioList.json"
    },
    {
        "id": 1,
        "name": "Finland",
        "flag": "https://upload.wikimedia.org/wikipedia/commons/thumb/b/bc/Flag_of_Finland.svg/1200px-Flag_of_Finland.svg.png",
        "url": "finlandRadioList.json"
    },
    {
        "id": 1,
        "name": "Moldova",
        "flag": "https://cdn11.bigcommerce.com/s-w6fxwapwzi/images/stencil/1280x1280/products/2952/5912/2x3-moldova-flag-image__10674.1582737815.jpg?c=1",
        "url": "moldovaRadioList.json"
    },
    {
        "id": 2,
        "name": "Romania",
        "flag": "https://encrypted-tbn0.gstatic.com/images?q=tbn:ANd9GcQ8SQe9t8pdHxfapZ9zqA0AMjJpLJzwrcOOlieswXWc5g&s",
        "url": "RomanianRadioList.json"
    },
    {
        "id": 3,
        "name": "Dominican Republic",
        "flag": "https://cdn.britannica.com/14/5114-004-C9B99800/Flag-Dominican-Republic.jpg",
        "url": "DominicanRepublicRadioList.json"
    },
    {
        "id": 4,
        "name": "United kingdom",
        "flag": "https://upload.wikimedia.org/wikipedia/commons/thumb/a/a5/Flag_of_the_United_Kingdom_%281-2%29.svg/1200px-Flag_of_the_United_Kingdom_%281-2%29.svg.png",
        "url": "ukRadioList.json"
    },
    {
        "id": 5,
        "name": "Turkey",
        "flag": "https://encrypted-tbn0.gstatic.com/images?q=tbn:ANd9GcQc0G8aE5AoGDOQMJGd8fcrO5rZOWWvrAVKUw&s",
        "url": "new_istanbulRadioList.json"
    },
    {
        "id": 6,
        "name": "Norway",
        "flag": "https://upload.wikimedia.org/wikipedia/commons/thumb/d/d9/Flag_of_Norway.svg/468px-Flag_of_Norway.svg.png",
        "url": "norwayRadioList.json"
    },
    {
        "id": 7,
        "name": "Canada",
        "flag": "https://www.worldatlas.com/img/flag/ca-flag.jpg",
        "url": "canadaRadioList.json"
    },
    {
        "id": 8,
        "name": "Bermuda",
        "flag": "https://img.freepik.com/premium-vector/bermuda-flag-official-national-flag-international-flag-world-flag-icon_970323-155.jpg",
        "url": "bermudaRadioList.json"
    },
    {
        "id": 9,
        "name": "Australia",
        "flag": "https://i.ebayimg.com/images/g/k-wAAOSwWWxhFZgJ/s-l1600.jpg",
        "url": "australiaRadioLit.json"
    },
    {
        "id": 10,
        "name": "Malaysia",
        "flag": "https://upload.wikimedia.org/wikipedia/commons/thumb/6/66/Flag_of_Malaysia.svg/1200px-Flag_of_Malaysia.svg.png",
        "url": "malaysianRadioList.json"
    },
    {
        "id": 13,
        "name": "Ukraine",
        "flag": "https://upload.wikimedia.org/wikipedia/commons/thumb/4/49/Flag_of_Ukraine.svg/2560px-Flag_of_Ukraine.svg.png",
        "url": "ukraineRadioList.json"
    },
    {
        "id": 14,
        "name": "Mexico",
        "flag": "https://upload.wikimedia.org/wikipedia/commons/thumb/1/17/Flag_of_Mexico.png/1200px-Flag_of_Mexico.png",
        "url": "mexicanRadioList.json"
    },
    {
        "id": 16,
        "name": "Rwanda",
        "flag": "https://upload.wikimedia.org/wikipedia/commons/thumb/1/17/Flag_of_Rwanda.svg/1200px-Flag_of_Rwanda.svg.png",
        "url": "rwandaRadioList.json"
    },
    {
        "id": 17,
        "name": "Swaziland",
        "flag": "https://media.istockphoto.com/id/1368280191/vector/flag-of-eswatini-national-flag-vector-illustration.jpg?s=612x612&w=0&k=20&c=E7TMU_koZ6--F0v69Fp9rJwXhBeFYsxNkLiTNjO57Iw=",
        "url": "swanzilandRadioList.json"
    },
    {
        "id": 18,
        "name": "Tunisia",
        "flag": "https://upload.wikimedia.org/wikipedia/commons/thumb/c/ce/Flag_of_Tunisia.svg/225px-Flag_of_Tunisia.svg.png",
        "url": "tunisiaRadioListEdited.json"
    },
    {
        "id": 19,
        "name": "Brasil",
        "flag": "https://cdn.britannica.com/47/6847-004-7D668BB0/Flag-Brazil.jpg",
        "url": "brazilradiolist.json"
    },
    {
        "id": 20,
        "name": "Germany",
        "flag": "https://cdn.britannica.com/82/65482-050-E43AB312/Flag-detail-Germany-crest.jpg",
        "url": "germanyRadioList.json"
    },
    {
        "id": 21,
        "name": "India",
        "flag": "https://upload.wikimedia.org/wikipedia/en/thumb/4/41/Flag_of_India.svg/1200px-Flag_of_India.svg.png",
        "url": "indiaradiolist.json"
    },
    {
        "id": 22,
        "name": "Phillipines",
        "flag": "https://img.freepik.com/free-photo/view-philippines-flag_23-2150425524.jpg?size=626&ext=jpg&ga=GA1.1.1395880969.1709510400&semt=ais",
        "url": "morRadio.json"
    },
    {
        "id": 23,
        "name": "Jamaica",
        "flag": "https://upload.wikimedia.org/wikipedia/commons/thumb/0/0a/Flag_of_Jamaica.svg/800px-Flag_of_Jamaica.svg.png",
        "url": "jamaicanRadioList.json"
    },
    {
        "id": 24,
        "name": "Cape-Verde",
        "flag": "https://encrypted-tbn0.gstatic.com/images?q=tbn:ANd9GcT872cqZS2O1-fXRbODKZf5jXTiP_jn6HsRmg&usqp=CAU",
        "url": "RCV - Rádio de Cabo Verde.json"
    },
    {
        "id": 25,
        "name": "Argentina",
        "flag": "https://cdn.britannica.com/69/5869-004-7D75CD05/Flag-Argentina.jpg",
        "url": "usaRadioList.json"
    },
    {
        "id": 26,
        "name": "Portugal",
        "flag": "https://img.freepik.com/premium-vector/portugal-flag-vector_654626-166.jpg",
        "url": "portugalRadioList.json"
    },
    {
        "id": 400000,
        "name": "",
        "flag": "https://upload.wikimedia",
        "url": ""
    }
]
